<?xml version="1.0" encoding="UTF-8"?><metadata>	<assets>		<detail id="1">			<x>33</x>			<y>322</y>			<width>649</width>			<height>370</height>			<s>blue</s>		</detail>		<detail id="2">			<x>217</x>			<y>163</y>			<width>451</width>			<height>327</height>			<s>yellow</s>		</detail>		<detail id="3">			<x>132</x>			<y>402</y>			<width>216</width>			<height>143</height>			<s>red</s>		</detail>		<detail id="4">			<x>465</x>			<y>35</y>			<width>186</width>			<height>184</height>			<s>green</s>		</detail>		<detail id="5">			<x>248</x>			<y>528</y>			<width>145</width>			<height>151</height>			<s>white</s>		</detail>	</assets>	<frame>			<s>ship</s>			<x>33</x>		<y>35</y>		<width>649</width>		<height>657</height>	</frame></metadata>	